{
"nexml": {
"@about": "#study", 
"@generator": "Phylografter nexml-json exporter", 
"@id": "study", 
"@nexmljson": "http://opentree.wikispaces.com/NexSON", 
"@version": "0.9", 
"@xmlns": {
"$": "http://www.nexml.org/2009", 
"nex": "http://www.nexml.org/2009", 
"ot": "http://purl.org/opentree-terms#", 
"xsd": "http://www.w3.org/2001/XMLSchema#", 
"xsi": "http://www.w3.org/2001/XMLSchema-instance"
}, 
"meta": [
{
"$": "Vizzini A., & Ercole E. 2011. A new taxon in the Infundibulicybe gibba complex (Basidiomycota, Agaricales, Tricholomataceae) from Sardinia (Italy). Mycologia, 103(1): 203-208.", 
"@property": "ot:studyPublicationReference", 
"@xsi:type": "nex:LiteralMeta"
}, 
{
"@href": "http://dx.doi.org/10.3852/10-137", 
"@property": "ot:studyPublication", 
"@xsi:type": "nex:ResourceMeta"
}, 
{
"$": "Romina Gazis", 
"@property": "ot:curatorName", 
"@xsi:type": "nex:LiteralMeta"
}, 
{
"@href": "http://purl.org/phylo/treebase/phylows/study/TB2:S10680", 
"@property": "ot:dataDeposit", 
"@xsi:type": "nex:ResourceMeta"
}, 
{
"$": "538", 
"@property": "ot:studyId", 
"@xsi:type": "nex:LiteralMeta"
}, 
{
"$": 2011, 
"@property": "ot:studyYear", 
"@xsi:type": "nex:LiteralMeta"
}, 
{
"$": 1115365, 
"@property": "ot:focalClade", 
"@xsi:type": "nex:LiteralMeta"
}, 
{
"$": "BI", 
"@property": "ot:tag", 
"@xsi:type": "nex:LiteralMeta"
}, 
{
"$": "ITS", 
"@property": "ot:tag", 
"@xsi:type": "nex:LiteralMeta"
}
], 
"otus": {
"@id": "otus538", 
"otu": [
{
"@about": "#otu169519", 
"@id": "otu169519", 
"@label": "Infundibulicybe gibba", 
"meta": [
{
"$": 462735, 
"@property": "ot:ottolid", 
"@xsi:type": "nex:LiteralMeta"
}, 
{
"$": "Infundibulicybe gibba A", 
"@property": "ot:originalLabel", 
"@xsi:type": "nex:LiteralMeta"
}
]
}, 
{
"@about": "#otu169520", 
"@id": "otu169520", 
"@label": "Infundibulicybe gibba", 
"meta": [
{
"$": 462735, 
"@property": "ot:ottolid", 
"@xsi:type": "nex:LiteralMeta"
}, 
{
"$": "Infundibulicybe gibba N", 
"@property": "ot:originalLabel", 
"@xsi:type": "nex:LiteralMeta"
}
]
}, 
{
"@about": "#otu169521", 
"@id": "otu169521", 
"@label": "Infundibulicybe gibba", 
"meta": [
{
"$": 462735, 
"@property": "ot:ottolid", 
"@xsi:type": "nex:LiteralMeta"
}, 
{
"$": "Infundibulicybe gibba DQ490635", 
"@property": "ot:originalLabel", 
"@xsi:type": "nex:LiteralMeta"
}
]
}, 
{
"@about": "#otu169522", 
"@id": "otu169522", 
"@label": "Clitocybe nebularis", 
"meta": [
{
"$": 909208, 
"@property": "ot:ottolid", 
"@xsi:type": "nex:LiteralMeta"
}, 
{
"$": "Lepista nebularis DQ149728", 
"@property": "ot:originalLabel", 
"@xsi:type": "nex:LiteralMeta"
}
]
}, 
{
"@about": "#otu169523", 
"@id": "otu169523", 
"@label": "Infundibulicybe gibba", 
"meta": [
{
"$": 462735, 
"@property": "ot:ottolid", 
"@xsi:type": "nex:LiteralMeta"
}, 
{
"$": "Infundibulicybe gibba B", 
"@property": "ot:originalLabel", 
"@xsi:type": "nex:LiteralMeta"
}
]
}, 
{
"@about": "#otu169524", 
"@id": "otu169524", 
"@label": "Infundibulicybe gibba", 
"meta": [
{
"$": 462735, 
"@property": "ot:ottolid", 
"@xsi:type": "nex:LiteralMeta"
}, 
{
"$": "Infundibulicybe gibba F", 
"@property": "ot:originalLabel", 
"@xsi:type": "nex:LiteralMeta"
}
]
}, 
{
"@about": "#otu169525", 
"@id": "otu169525", 
"@label": "Infundibulicybe gibba", 
"meta": [
{
"$": 462735, 
"@property": "ot:ottolid", 
"@xsi:type": "nex:LiteralMeta"
}, 
{
"$": "Infundibulicybe gibba H", 
"@property": "ot:originalLabel", 
"@xsi:type": "nex:LiteralMeta"
}
]
}, 
{
"@about": "#otu169526", 
"@id": "otu169526", 
"@label": "Infundibulicybe gibba", 
"meta": [
{
"$": 462735, 
"@property": "ot:ottolid", 
"@xsi:type": "nex:LiteralMeta"
}, 
{
"$": "Infundibulicybe gibba AB301608", 
"@property": "ot:originalLabel", 
"@xsi:type": "nex:LiteralMeta"
}
]
}, 
{
"@about": "#otu169527", 
"@id": "otu169527", 
"@label": "Infundibulicybe catinus", 
"meta": [
{
"$": 570237, 
"@property": "ot:ottolid", 
"@xsi:type": "nex:LiteralMeta"
}, 
{
"$": "Infundibulicybe catinus I", 
"@property": "ot:originalLabel", 
"@xsi:type": "nex:LiteralMeta"
}
]
}, 
{
"@about": "#otu169528", 
"@id": "otu169528", 
"@label": "Infundibulicybe gibba", 
"meta": [
{
"$": 462735, 
"@property": "ot:ottolid", 
"@xsi:type": "nex:LiteralMeta"
}, 
{
"$": "Infundibulicybe gibba M", 
"@property": "ot:originalLabel", 
"@xsi:type": "nex:LiteralMeta"
}
]
}, 
{
"@about": "#otu169529", 
"@id": "otu169529", 
"@label": "Infundibulicybe gibba", 
"meta": [
{
"$": 462735, 
"@property": "ot:ottolid", 
"@xsi:type": "nex:LiteralMeta"
}, 
{
"$": "Infundibulicybe gibba FJ596815", 
"@property": "ot:originalLabel", 
"@xsi:type": "nex:LiteralMeta"
}
]
}, 
{
"@about": "#otu169530", 
"@id": "otu169530", 
"@label": "Infundibulicybe gibba", 
"meta": [
{
"$": 462735, 
"@property": "ot:ottolid", 
"@xsi:type": "nex:LiteralMeta"
}, 
{
"$": "Infundibulicybe gibba E", 
"@property": "ot:originalLabel", 
"@xsi:type": "nex:LiteralMeta"
}
]
}, 
{
"@about": "#otu169531", 
"@id": "otu169531", 
"@label": "Infundibulicybe mediterranea", 
"meta": [
{
"$": 140322, 
"@property": "ot:ottolid", 
"@xsi:type": "nex:LiteralMeta"
}, 
{
"$": "Infundibulicybe mediterranea O", 
"@property": "ot:originalLabel", 
"@xsi:type": "nex:LiteralMeta"
}
]
}, 
{
"@about": "#otu169532", 
"@id": "otu169532", 
"@label": "Infundibulicybe gibba", 
"meta": [
{
"$": 462735, 
"@property": "ot:ottolid", 
"@xsi:type": "nex:LiteralMeta"
}, 
{
"$": "Infundibulicybe gibba C", 
"@property": "ot:originalLabel", 
"@xsi:type": "nex:LiteralMeta"
}
]
}, 
{
"@about": "#otu169533", 
"@id": "otu169533", 
"@label": "Infundibulicybe gibba", 
"meta": [
{
"$": 462735, 
"@property": "ot:ottolid", 
"@xsi:type": "nex:LiteralMeta"
}, 
{
"$": "Infundibulicybe gibba D", 
"@property": "ot:originalLabel", 
"@xsi:type": "nex:LiteralMeta"
}
]
}, 
{
"@about": "#otu169534", 
"@id": "otu169534", 
"@label": "Infundibulicybe gibba", 
"meta": [
{
"$": 462735, 
"@property": "ot:ottolid", 
"@xsi:type": "nex:LiteralMeta"
}, 
{
"$": "Infundibulicybe gibba G", 
"@property": "ot:originalLabel", 
"@xsi:type": "nex:LiteralMeta"
}
]
}, 
{
"@about": "#otu169535", 
"@id": "otu169535", 
"@label": "Infundibulicybe gibba", 
"meta": [
{
"$": 462735, 
"@property": "ot:ottolid", 
"@xsi:type": "nex:LiteralMeta"
}, 
{
"$": "Infundibulicybe gibba L", 
"@property": "ot:originalLabel", 
"@xsi:type": "nex:LiteralMeta"
}
]
}, 
{
"@about": "#otu169536", 
"@id": "otu169536", 
"@label": "Infundibulicybe gibba", 
"meta": [
{
"$": 462735, 
"@property": "ot:ottolid", 
"@xsi:type": "nex:LiteralMeta"
}, 
{
"$": "Infundibulicybe gibba GU188436", 
"@property": "ot:originalLabel", 
"@xsi:type": "nex:LiteralMeta"
}
]
}, 
{
"@about": "#otu169537", 
"@id": "otu169537", 
"@label": "Lepista irina", 
"meta": [
{
"$": 675654, 
"@property": "ot:ottolid", 
"@xsi:type": "nex:LiteralMeta"
}, 
{
"$": "Lepista irina FJ810142", 
"@property": "ot:originalLabel", 
"@xsi:type": "nex:LiteralMeta"
}
]
}
]
}, 
"trees": {
"@id": "trees538", 
"@otus": "otus538", 
"tree": [
{
"@about": "#tree786", 
"@id": "tree786", 
"edge": [
{
"@id": "edge338136", 
"@length": 0.054936, 
"@source": "node338135", 
"@target": "node338136"
}, 
{
"@id": "edge338137", 
"@length": 0.059309, 
"@source": "node338135", 
"@target": "node338137"
}, 
{
"@id": "edge338138", 
"@length": 0.134801, 
"@source": "node338135", 
"@target": "node338138"
}, 
{
"@id": "edge338139", 
"@length": 0.012902, 
"@source": "node338138", 
"@target": "node338139"
}, 
{
"@id": "edge338140", 
"@length": 0.016143, 
"@source": "node338139", 
"@target": "node338140"
}, 
{
"@id": "edge338141", 
"@length": 0.003214, 
"@source": "node338140", 
"@target": "node338141"
}, 
{
"@id": "edge338142", 
"@length": 0.003225, 
"@source": "node338141", 
"@target": "node338142"
}, 
{
"@id": "edge338143", 
"@length": 0.003225, 
"@source": "node338141", 
"@target": "node338143"
}, 
{
"@id": "edge338144", 
"@length": 0.001652, 
"@source": "node338141", 
"@target": "node338144"
}, 
{
"@id": "edge338145", 
"@length": 0.001661, 
"@source": "node338141", 
"@target": "node338145"
}, 
{
"@id": "edge338146", 
"@length": 0.003319, 
"@source": "node338141", 
"@target": "node338146"
}, 
{
"@id": "edge338147", 
"@length": 0.001619, 
"@source": "node338141", 
"@target": "node338147"
}, 
{
"@id": "edge338148", 
"@length": 0.003233, 
"@source": "node338140", 
"@target": "node338148"
}, 
{
"@id": "edge338149", 
"@length": 0.001671, 
"@source": "node338148", 
"@target": "node338149"
}, 
{
"@id": "edge338150", 
"@length": 0.001643, 
"@source": "node338148", 
"@target": "node338150"
}, 
{
"@id": "edge338151", 
"@length": 0.003263, 
"@source": "node338140", 
"@target": "node338151"
}, 
{
"@id": "edge338152", 
"@length": 0.001621, 
"@source": "node338140", 
"@target": "node338152"
}, 
{
"@id": "edge338153", 
"@length": 0.00162, 
"@source": "node338140", 
"@target": "node338153"
}, 
{
"@id": "edge338154", 
"@length": 0.001627, 
"@source": "node338140", 
"@target": "node338154"
}, 
{
"@id": "edge338155", 
"@length": 0.005486, 
"@source": "node338139", 
"@target": "node338155"
}, 
{
"@id": "edge338156", 
"@length": 0.001642, 
"@source": "node338139", 
"@target": "node338156"
}, 
{
"@id": "edge338157", 
"@length": 0.00179, 
"@source": "node338139", 
"@target": "node338157"
}, 
{
"@id": "edge338158", 
"@length": 0.001664, 
"@source": "node338139", 
"@target": "node338158"
}, 
{
"@id": "edge338159", 
"@length": 0.041218, 
"@source": "node338138", 
"@target": "node338159"
}
], 
"meta": [
{
"$": "node338138", 
"@property": "ot:inGroupClade", 
"@xsi:type": "nex:LiteralMeta"
}, 
{
"$": "BI", 
"@property": "ot:tag", 
"@xsi:type": "nex:LiteralMeta"
}, 
{
"$": "ITS", 
"@property": "ot:tag", 
"@xsi:type": "nex:LiteralMeta"
}
], 
"node": [
{
"@id": "node338135", 
"@root": "true"
}, 
{
"@id": "node338136", 
"@otu": "otu169522"
}, 
{
"@id": "node338137", 
"@otu": "otu169537"
}, 
{
"@id": "node338138"
}, 
{
"@id": "node338139"
}, 
{
"@id": "node338140"
}, 
{
"@id": "node338141"
}, 
{
"@id": "node338142", 
"@otu": "otu169519"
}, 
{
"@id": "node338143", 
"@otu": "otu169523"
}, 
{
"@id": "node338144", 
"@otu": "otu169532"
}, 
{
"@id": "node338145", 
"@otu": "otu169533"
}, 
{
"@id": "node338146", 
"@otu": "otu169530"
}, 
{
"@id": "node338147", 
"@otu": "otu169524"
}, 
{
"@id": "node338148"
}, 
{
"@id": "node338149", 
"@otu": "otu169534"
}, 
{
"@id": "node338150", 
"@otu": "otu169525"
}, 
{
"@id": "node338151", 
"@otu": "otu169527"
}, 
{
"@id": "node338152", 
"@otu": "otu169535"
}, 
{
"@id": "node338153", 
"@otu": "otu169528"
}, 
{
"@id": "node338154", 
"@otu": "otu169520"
}, 
{
"@id": "node338155", 
"@otu": "otu169526"
}, 
{
"@id": "node338156", 
"@otu": "otu169536"
}, 
{
"@id": "node338157", 
"@otu": "otu169521"
}, 
{
"@id": "node338158", 
"@otu": "otu169529"
}, 
{
"@id": "node338159", 
"@otu": "otu169531"
}
]
}
]
}
}
}